odoo10_addon_hotel_restaurant-10.0.1.0.0.99.dev18-py2.7-nspkg.pth
odoo/addons/hotel_restaurant/README.rst
odoo/addons/hotel_restaurant/__init__.py
odoo/addons/hotel_restaurant/__manifest__.py
odoo/addons/hotel_restaurant/Doc/ChangeLog.txt
odoo/addons/hotel_restaurant/LICENSE/LICENSE
odoo/addons/hotel_restaurant/i18n/es.po
odoo/addons/hotel_restaurant/i18n/fr_BE.po
odoo/addons/hotel_restaurant/i18n/sv.po
odoo/addons/hotel_restaurant/models/__init__.py
odoo/addons/hotel_restaurant/models/hotel_restaurant.py
odoo/addons/hotel_restaurant/report/__init__.py
odoo/addons/hotel_restaurant/report/hotel_restaurant_report.py
odoo/addons/hotel_restaurant/report/hotel_restaurant_report.xml
odoo/addons/hotel_restaurant/security/ir.model.access.csv
odoo/addons/hotel_restaurant/static/description/icon.png
odoo/addons/hotel_restaurant/static/description/res1.png
odoo/addons/hotel_restaurant/static/description/res2.png
odoo/addons/hotel_restaurant/static/description/res3.png
odoo/addons/hotel_restaurant/static/description/res4.png
odoo/addons/hotel_restaurant/static/description/res5.png
odoo/addons/hotel_restaurant/static/description/res6.png
odoo/addons/hotel_restaurant/static/description/serpent.png
odoo/addons/hotel_restaurant/static/img/Halva.jpg
odoo/addons/hotel_restaurant/static/img/Idli_sambar.jpg
odoo/addons/hotel_restaurant/static/img/appam1.jpg
odoo/addons/hotel_restaurant/static/img/bhaji_paw.jpg
odoo/addons/hotel_restaurant/static/img/chees_masala.jpg
odoo/addons/hotel_restaurant/static/img/chole.png
odoo/addons/hotel_restaurant/static/img/dosa.png
odoo/addons/hotel_restaurant/static/img/khandvi.jpg
odoo/addons/hotel_restaurant/static/img/malai_kofta.jpg
odoo/addons/hotel_restaurant/static/img/masala_kulcha.jpg
odoo/addons/hotel_restaurant/static/img/muttter_paneer.png
odoo/addons/hotel_restaurant/static/img/paneer_bhurji.jpg
odoo/addons/hotel_restaurant/static/img/paneer_butter_masala.jpg
odoo10_addon_hotel_restaurant-10.0.1.0.0.99.dev18.dist-info/DESCRIPTION.rst
odoo10_addon_hotel_restaurant-10.0.1.0.0.99.dev18.dist-info/METADATA
odoo10_addon_hotel_restaurant-10.0.1.0.0.99.dev18.dist-info/RECORD
odoo10_addon_hotel_restaurant-10.0.1.0.0.99.dev18.dist-info/WHEEL
odoo10_addon_hotel_restaurant-10.0.1.0.0.99.dev18.dist-info/metadata.json
odoo10_addon_hotel_restaurant-10.0.1.0.0.99.dev18.dist-info/namespace_packages.txt
odoo10_addon_hotel_restaurant-10.0.1.0.0.99.dev18.dist-info/top_level.txt
